sinling/__init__.py
sinling/config.py
sinling/utils.py
sinling/core/__init__.py
sinling/core/joiner.py
sinling/core/splitter.py
sinling/core/stemmer.py
sinling/core/tagger.py
sinling/core/tokenizer.py
sinling/resources/pos-tagger-crf-sinling.joblib
sinling/resources/stat.split.pickle
sinling/resources/stem_dictionary.txt
sinling/resources/suffixes_list.txt
sinling/sinhala/__init__.py
sinling/sinhala/joiner.py
sinling/sinhala/letters.py
sinling/sinhala/preprocess.py
sinling/sinhala/splitter.py
sinling/sinhala/stemmer.py
sinling/sinhala/tagger.py
sinling/sinhala/tokenizer.py
sinling-0.3.6.dist-info/LICENSE
sinling-0.3.6.dist-info/METADATA
sinling-0.3.6.dist-info/WHEEL
sinling-0.3.6.dist-info/top_level.txt
sinling-0.3.6.dist-info/RECORD
