Metadata-Version: 2.1
Name: sinling
Version: 0.3.6
Summary: A language processing tool for Sinhalese (සිංහල)
Home-page: https://github.com/ysenarath/sinling
Author: Yasas Senarath
License: UNKNOWN
Platform: UNKNOWN
Classifier: Programming Language :: Python :: 3
Classifier: Operating System :: OS Independent
Requires-Python: >=3.6
